<?xml version="1.0" encoding="UTF-8" ?>
<!DOCTYPE mapper
PUBLIC "-//mybatis.org//DTD Mapper 3.0//EN"
"http://mybatis.org/dtd/mybatis-3-mapper.dtd">
<mapper namespace="com.medusa.mall.mapper.CategoryMapper">
    
    <resultMap type="Category" id="CategoryResult">
        <result property="id" column="id"/>
        <result property="categoryName" column="category_name"/>
        <result property="categoryCode" column="category_code"/>
        <result property="description" column="description"/>
        <result property="imageUrl" column="image_url"/>
        <result property="iconUrl" column="icon_url"/>
        <result property="status" column="status"/>
        <result property="sortOrder" column="sort_order"/>
        <result property="isFeatured" column="is_featured"/>
        <result property="createBy" column="create_by"/>
        <result property="createTime" column="create_time"/>
        <result property="updateBy" column="update_by"/>
        <result property="updateTime" column="update_time"/>
        <result property="remark" column="remark"/>
    </resultMap>

    <sql id="selectCategoryVo">
        select id, category_name, category_code, description, image_url, icon_url, 
               status, sort_order, is_featured, create_by, create_time, update_by, update_time, remark
        from mall_category
    </sql>

    <select id="selectCategoryList" parameterType="Category" resultMap="CategoryResult">
        <include refid="selectCategoryVo"/>
        <where>
            <if test="categoryName != null and categoryName != ''">
                AND category_name like concat('%', #{categoryName}, '%')
            </if>
            <if test="categoryCode != null and categoryCode != ''">
                AND category_code = #{categoryCode}
            </if>
            <if test="status != null">
                AND status = #{status}
            </if>
            <if test="isFeatured != null">
                AND is_featured = #{isFeatured}
            </if>
        </where>
        order by sort_order asc, create_time desc
    </select>

    <select id="selectCategoryById" parameterType="Long" resultMap="CategoryResult">
        <include refid="selectCategoryVo"/>
        where id = #{id}
    </select>

    <select id="selectCategoryByCode" parameterType="String" resultMap="CategoryResult">
        <include refid="selectCategoryVo"/>
        where category_code = #{categoryCode}
    </select>

    <select id="selectActiveCategories" resultMap="CategoryResult">
        <include refid="selectCategoryVo"/>
        where status = 1
        order by sort_order asc, create_time desc
    </select>

    <insert id="insertCategory" parameterType="Category" useGeneratedKeys="true" keyProperty="id">
        insert into mall_category(
            <if test="categoryName != null and categoryName != ''">category_name,</if>
            <if test="categoryCode != null and categoryCode != ''">category_code,</if>
            <if test="description != null and description != ''">description,</if>
            <if test="imageUrl != null and imageUrl != ''">image_url,</if>
            <if test="iconUrl != null and iconUrl != ''">icon_url,</if>
            <if test="status != null">status,</if>
            <if test="sortOrder != null">sort_order,</if>
            <if test="isFeatured != null">is_featured,</if>
            <if test="createBy != null and createBy != ''">create_by,</if>
            <if test="remark != null and remark != ''">remark,</if>
            create_time
        ) values (
            <if test="categoryName != null and categoryName != ''">#{categoryName},</if>
            <if test="categoryCode != null and categoryCode != ''">#{categoryCode},</if>
            <if test="description != null and description != ''">#{description},</if>
            <if test="imageUrl != null and imageUrl != ''">#{imageUrl},</if>
            <if test="iconUrl != null and iconUrl != ''">#{iconUrl},</if>
            <if test="status != null">#{status},</if>
            <if test="sortOrder != null">#{sortOrder},</if>
            <if test="isFeatured != null">#{isFeatured},</if>
            <if test="createBy != null and createBy != ''">#{createBy},</if>
            <if test="remark != null and remark != ''">#{remark},</if>
            sysdate()
        )
    </insert>

    <update id="updateCategory" parameterType="Category">
        update mall_category
        <trim prefix="SET" suffixOverrides=",">
            <if test="categoryName != null and categoryName != ''">category_name = #{categoryName},</if>
            <if test="categoryCode != null and categoryCode != ''">category_code = #{categoryCode},</if>
            <if test="description != null and description != ''">description = #{description},</if>
            <if test="imageUrl != null and imageUrl != ''">image_url = #{imageUrl},</if>
            <if test="iconUrl != null and iconUrl != ''">icon_url = #{iconUrl},</if>
            <if test="status != null">status = #{status},</if>
            <if test="sortOrder != null">sort_order = #{sortOrder},</if>
            <if test="isFeatured != null">is_featured = #{isFeatured},</if>
            <if test="updateBy != null and updateBy != ''">update_by = #{updateBy},</if>
            <if test="remark != null and remark != ''">remark = #{remark},</if>
            update_time = sysdate()
        </trim>
        where id = #{id}
    </update>

    <delete id="deleteCategoryById" parameterType="Long">
        delete from mall_category where id = #{id}
    </delete>

    <delete id="deleteCategoryByIds" parameterType="String">
        delete from mall_category where id in 
        <foreach item="id" collection="array" open="(" separator="," close=")">
            #{id}
        </foreach>
    </delete>

</mapper> 